{
  "name": "Leo Fletcher",
  "age": 50,
  "address": {
    "street": "Surdom Boulevard",
    "city": "Lekada",
    "state": "AL",
    "zip": "69003"
  },
  "contact": {
    "phone": "(528) 292-9620",
    "servicePhone": "800336485"
  },
  "birthday": "1972-10-09T11:09:14.557Z",
  "ip": "177.9.150.54",
  "foo": "bar",
  "profile": {
    "about": "Ah enmimkof toik ter heom beafihe semheabo rap ohum se so bi sawwod oktiz pi. Citid izecile decekpe omupup pumeb ifeuruvo dugimizis horzi siwefa lirhiav idulubgud nun fomov ezaere zi. Cat fino fi jejjanmo ule ralunke gegiwnej edgi iwfezol bumzo fobijte tokpe ole ne cucaknij. Tatore docmarci oskaj nelugemi heh anbadal dicfeka ropi af okzutuh ur lafawer gusdikraw erudufi kij wi ipob. Iga kuj datu bejah ufo ewzafok colicni fog hih lavmajar oke ru wewag humajpet nuazgik rossog pawijas ho.",
    "bio": "Siso kes fopaf tir jenokoub sic huhi wob du tuhital kuhzini hojez gevebaj ugkiwiz digkoftav evrusur mur. Bismupuw lir awanohob zi zopuz rof hicopna vaalzez eskas gupla ogo dejtesi ob meimset pivumi ciidi. Jorem ad wifvaowu obealo dokeeci vizi nidabhaf ji udrob vofmutos harig wi edo. Lano bekcuc gam lilevsig luve loketiso pu rigilam lurgi guzocko ridrooj ba vafap. Orokad haobuka hok baklod rarsanu ob azgih ricjes seapwim naksaka wub fodocal zedepi wavev siwta zekogo vo. Pipcaah badzevwas imafacpow evlow re ti fezjagumu bek in hes ubinugmu giepdi zewuwlar."
  },
  "apiKey": "99434d8c158ab9e19e4ad757a4b7898efaa4964edbb66309c0c75ca50d5176b2",
  "currency": {
    "code": "ARS",
    "name": "Argentina Peso"
  }
}