{
  "name": "Wayne Taylor",
  "age": 44,
  "address": {
    "street": "Riuv View",
    "city": "Udloveve",
    "state": "DE",
    "zip": "56096"
  },
  "contact": {
    "phone": "(571) 634-1144",
    "servicePhone": "800893196"
  },
  "birthday": "1987-02-10T11:40:40.037Z",
  "ip": "196.9.25.145",
  "foo": "bar",
  "profile": {
    "about": "Sameami ah uf sulba nos wil uduli uc gatfe laeg rusose sefduv mogifle za cu ku did mede. Gigesuwa kopzuripa igiwushug sawap ne bimifdo anu cotocji suanu bujakad zawsas aspop rezoster ra favevfiw nonig dif porle. Tew pif dicfaf sanwa uki zadgucto golovec nuforuf ozmeaz abo civeib huvosmar. Fim ibimofik didozok wemholi obcuvhe ziarugo ihi jikulan ita bute ifimi wubusvik man dagkupe ihegi.",
    "bio": "Jaklutup ligtudzih sag ahir sogmojwaw ja id vujuje fi muroh zu mip. Mutlap zu ag vepbaluc lav ke ehomba vewco mujo elu aj isi. Cem cinjag wo lik dur votu gaoraeg atu ge keroru ketgis emepa nujop vuepibi koir. Hazreh pe aga akzat boikuvu rurmavoto re viwasvu nami jiac ube caig ozukufta uko bonetfir. Rum pe akcikus curco besjovzam pe modrenoje ol bopi jaesu ahuitvom cut me ritucnu."
  },
  "apiKey": "b5d5ec40e3feaff226bc8ffb1575907b1e8d8f4278f45f515f9beab051c28285",
  "currency": {
    "code": "CHF",
    "name": "Switzerland Franc"
  }
}